setup.py
linkedin_pkg/__init__.py
linkedin_pkg/linkedin.py
linkedin_pkg.egg-info/PKG-INFO
linkedin_pkg.egg-info/SOURCES.txt
linkedin_pkg.egg-info/dependency_links.txt
linkedin_pkg.egg-info/not-zip-safe
linkedin_pkg.egg-info/top_level.txt