Metadata-Version: 1.1
Name: linkedin-pkg
Version: 0.1.1
Summary: Create a LinkedIn account with a searchable network
Home-page: UNKNOWN
Author: Alex Katona
Author-email: UNKNOWN
License: UNKNOWN
Keywords: networking social
Platform: UNKNOWN
Classifier: Development Status :: 2 - Pre-Alpha
Classifier: Programming Language :: Python :: 3.5
Classifier: Intended Audience :: Science/Research
Classifier: Natural Language :: English
